exclock/__init__.py
exclock/assets/clock/3m.json5
exclock/assets/clock/5m.json5
exclock/assets/clock/pomodoro.json5
exclock/assets/clock/warning.json5
exclock/assets/sound/ring.mp3
exclock/assets/sound/silent.mp3
exclock/entities.py
exclock/main.py
exclock/mains/__init__.py
exclock/mains/play_clock_main.py
exclock/mains/show_list_main.py
exclock/mains/specified_time_main.py
exclock/schemas/cerberus_clock_schema.py
exclock/sound_player.py
exclock/util.py
exclock-0.4.6.dist-info/entry_points.txt
exclock-0.4.6.dist-info/LICENSE
exclock-0.4.6.dist-info/WHEEL
exclock-0.4.6.dist-info/METADATA
exclock-0.4.6.dist-info/RECORD
