Metadata-Version: 2.1
Name: exclock
Version: 0.4.6
Summary: exclock is a cui extended timer.
Home-page: https://gitlab.com/yassu/exclock
License: Apache-2.0
Keywords: timer,clock,notification
Author: yassu
Author-email: yasu0320.dev@gmail.com
Requires-Python: >=3.8,<4.0
Classifier: Development Status :: 3 - Alpha
Classifier: License :: OSI Approved :: Apache Software License
Classifier: Programming Language :: Python
Classifier: Programming Language :: Python :: 3
Classifier: Programming Language :: Python :: 3 :: Only
Classifier: Programming Language :: Python :: 3.8
Classifier: Programming Language :: Python :: 3.9
Classifier: Topic :: Terminals
Classifier: Topic :: Utilities
Requires-Dist: Cerberus (>=1.3.2,<2.0.0)
Requires-Dist: json5 (>=0.9.5,<0.10.0)
Requires-Dist: typer (>=0.3.2,<0.4.0)
Project-URL: Repository, https://gitlab.com/yassu/exclock
